README.rst
setup.py
django_simpletree.egg-info/PKG-INFO
django_simpletree.egg-info/SOURCES.txt
django_simpletree.egg-info/dependency_links.txt
django_simpletree.egg-info/top_level.txt
simpletree/__init__.py
simpletree/admin.py
simpletree/apps.py
simpletree/forms.py
simpletree/models.py
simpletree/tests.py